trancepoint/__init__.py
trancepoint/config.py
trancepoint/decorator.py
trancepoint/http_client.py
trancepoint/models.py
trancepoint/pricing.py
trancepoint/utils.py
trancepoint/wrapper.py
trancepoint-0.1.5.dist-info/licenses/LICENSE
trancepoint-0.1.5.dist-info/METADATA
trancepoint-0.1.5.dist-info/WHEEL
trancepoint-0.1.5.dist-info/top_level.txt
trancepoint-0.1.5.dist-info/RECORD
