Metadata-Version: 2.4
Name: trancepoint
Version: 0.1.5
Summary: SDK for agent observability and monitoring with backend integration
Home-page: https://github.com/yourusername/agent-observability
Author: Your Name
Author-email: Pranay Rishith <pranayrishith81009@gmail.com>
License: MIT
Project-URL: Homepage, https://github.com/yourusername/agent-observability
Project-URL: Documentation, https://github.com/yourusername/agent-observability#readme
Project-URL: Repository, https://github.com/yourusername/agent-observability.git
Project-URL: Issues, https://github.com/yourusername/agent-observability/issues
Keywords: agent,observability,monitoring,analytics,ai
Classifier: Development Status :: 3 - Alpha
Classifier: Intended Audience :: Developers
Classifier: License :: OSI Approved :: MIT License
Classifier: Operating System :: OS Independent
Classifier: Programming Language :: Python :: 3
Classifier: Programming Language :: Python :: 3.8
Classifier: Programming Language :: Python :: 3.9
Classifier: Programming Language :: Python :: 3.10
Classifier: Programming Language :: Python :: 3.11
Classifier: Programming Language :: Python :: 3.12
Classifier: Topic :: Software Development :: Libraries :: Python Modules
Classifier: Topic :: Internet
Requires-Python: >=3.8
License-File: LICENSE
Requires-Dist: requests>=2.28.0
Requires-Dist: pydantic>=2.12.5
Requires-Dist: httpx==0.28.1
Requires-Dist: PyYAML==6.0.3
Requires-Dist: tiktoken==0.12.0
Provides-Extra: dev
Requires-Dist: pytest>=7.0; extra == "dev"
Requires-Dist: pytest-cov>=4.0; extra == "dev"
Requires-Dist: black>=23.0; extra == "dev"
Requires-Dist: ruff>=0.1.0; extra == "dev"
Requires-Dist: mypy>=1.0; extra == "dev"
Dynamic: author
Dynamic: home-page
Dynamic: license-file
Dynamic: requires-python
